{
  "project_info": {
    "project_number": "737467854806",
    "project_id": "notes-app-mvvm-bb706",
    "storage_bucket": "notes-app-mvvm-bb706.appspot.com"
  },
  "client": [
    {
      "client_info": {
        "mobilesdk_app_id": "1:737467854806:android:3c1c0638286c0980c1be77",
        "android_client_info": {
          "package_name": "com.example.notesappmvvm"
        }
      },
      "oauth_client": [
        {
          "client_id": "737467854806-e08sald89tkp2jf36m178sorb7c14gsp.apps.googleusercontent.com",
          "client_type": 3
        }
      ],
      "api_key": [
        {
          "current_key": "AIzaSyBuITwqOed_6D6u26xgbNW52c_KqkSWn0Q"
        }
      ],
      "services": {
        "appinvite_service": {
          "other_platform_oauth_client": [
            {
              "client_id": "737467854806-e08sald89tkp2jf36m178sorb7c14gsp.apps.googleusercontent.com",
              "client_type": 3
            }
          ]
        }
      }
    }
  ],
  "configuration_version": "1"
}